README
setup.py
mig/__init__.py
mig/models.py
mig/util.py
mig.egg-info/PKG-INFO
mig.egg-info/SOURCES.txt
mig.egg-info/dependency_links.txt
mig.egg-info/requires.txt
mig.egg-info/top_level.txt