Metadata-Version: 1.1
Name: mig
Version: 0.0.6
Summary: SQLAlchemy migrations
Home-page: https://github.com/jwandborg/mig/
Author: mig contributors
Author-email: joar@talka.tv
License: UNKNOWN
Platform: UNKNOWN
Classifier: License :: OSI Approved :: Apache Software License
Classifier: Programming Language :: Python
Classifier: Operating System :: OS Independent
Classifier: Topic :: Database
